webrtc_models/__init__.py
webrtc_models/py.typed
webrtc_models-0.2.0.dist-info/METADATA
webrtc_models-0.2.0.dist-info/WHEEL
webrtc_models-0.2.0.dist-info/licenses/LICENSE
webrtc_models-0.2.0.dist-info/RECORD
