Metadata-Version: 2.3
Name: webrtc-models
Version: 0.2.0
Summary: Python WebRTC models
Project-URL: Homepage, https://pypi.org/project/webrtc-models
Project-URL: Source Code, https://github.com/home-assistant-libs/python-webrtc-models
Project-URL: Bug Reports, https://github.com/home-assistant-libs/python-webrtc-models/issues
Author-email: Robert Resch <robert@resch.dev>
License: Apache-2.0
License-File: LICENSE
Keywords: webrtc
Classifier: Development Status :: 3 - Alpha
Classifier: Intended Audience :: Developers
Classifier: Programming Language :: Python :: 3.12
Requires-Python: >=3.12.0
Requires-Dist: mashumaro~=3.13
Requires-Dist: orjson>=3.10.7
